[
  {
    "title": "Etec - Escola Técnica - Guarujá",
    "link": "https://www.pciconcursos.com.br/noticias/etec-de-guaruja-sp-publica-abertura-de-inscricoes-para-dois-editais-de-processo-seletivo",
    "official_link": null,
    "end_date": "2026-06-16",
    "vacancies": null,
    "salary_text": "R$ 21,40",
    "salary_value": 21.4,
    "raw_text": "Etec - Escola Técnica - Guarujá SP Vagas até R$ 21,40 h/a Professores de Ensino Médio e Técnico Superior 02 a 16/06/2026",
    "positions": []
  },
  {
    "title": "USP - Universidade de São Paulo",
    "link": "https://www.pciconcursos.com.br/noticias/usp-promove-edital-de-concurso-publico-com-uma-vaga-para-cargo-de-professor",
    "official_link": null,
    "end_date": "2026-05-15",
    "vacancies": 1,
    "salary_text": "R$ 10.696,17",
    "salary_value": 10696.17,
    "raw_text": "USP - Universidade de São Paulo SP 1 vaga até R$ 10.696,17 Professor Titular Superior 15/05/2026",
    "positions": []
  },
  {
    "title": "USP - Universidade de São Paulo",
    "link": "https://www.pciconcursos.com.br/noticias/usp-publica-concurso-publico-com-uma-vaga-para-cargo-de-professor-titular",
    "official_link": null,
    "end_date": "2026-05-18",
    "vacancies": 1,
    "salary_text": "R$ 24.309,11",
    "salary_value": 24309.11,
    "raw_text": "USP - Universidade de São Paulo SP 1 vaga até R$ 24.309,11 Professor Titular (Língua e Literaturas Espanhola e Hispano-Americana) Superior 18/05/2026",
    "positions": []
  },
  {
    "title": "USP - Universidade de São Paulo",
    "link": "https://www.pciconcursos.com.br/noticias/usp-abre-quatro-concursos-publicos-para-professor-titular-na-escola-politecnica",
    "official_link": null,
    "end_date": "2026-05-12",
    "vacancies": 4,
    "salary_text": "R$ 24.309,11",
    "salary_value": 24309.11,
    "raw_text": "USP - Universidade de São Paulo SP 4 vagas até R$ 24.309,11 Vários Cargos Superior 12/05/2026",
    "positions": []
  },
  {
    "title": "USP - Universidade de São Paulo",
    "link": "https://www.pciconcursos.com.br/noticias/usp-abre-concurso-publico-com-uma-vaga-para-cargo-de-professor-titular",
    "official_link": null,
    "end_date": "2026-06-01",
    "vacancies": 1,
    "salary_text": "R$ 24.309,11",
    "salary_value": 24309.11,
    "raw_text": "USP - Universidade de São Paulo SP 1 vaga até R$ 24.309,11 Professor Titular Superior 01/06/2026",
    "positions": []
  },
  {
    "title": "USP - Universidade de São Paulo",
    "link": "https://www.pciconcursos.com.br/noticias/usp-promove-concurso-publico-para-professor-titular-na-area-de-ciencias-basicas-e-ambientais",
    "official_link": null,
    "end_date": "2026-06-15",
    "vacancies": 1,
    "salary_text": "R$ 24.309,11",
    "salary_value": 24309.11,
    "raw_text": "USP - Universidade de São Paulo SP 1 vaga até R$ 24.309,11 Professor Titular Superior 15/06/2026",
    "positions": []
  },
  {
    "title": "USP - Universidade de São Paulo",
    "link": "https://www.pciconcursos.com.br/noticias/usp-abre-concurso-publico-com-salarios-de-16353-para-professor-doutor",
    "official_link": null,
    "end_date": "2026-05-11",
    "vacancies": 3,
    "salary_text": "R$ 16.353,01",
    "salary_value": 16353.01,
    "raw_text": "USP - Universidade de São Paulo SP 3 vagas até R$ 16.353,01 Professor Doutor Superior 11/05/2026",
    "positions": []
  },
  {
    "title": "EESC-USP - Escola de Engenharia de São Carlos da Universidade de São Paulo",
    "link": "https://www.pciconcursos.com.br/noticias/usp-abre-vagas-para-professor-doutor-na-escola-de-engenharia-de-sao-carlos",
    "end_date": "2026-05-07",
    "vacancies": 2,
    "salary_text": "R$ 16.353,01",
    "salary_value": 16353.01
  },
  {
    "title": "EESC-USP - Escola de Engenharia de São Carlos da Universidade de São Paulo",
    "link": "https://www.pciconcursos.com.br/noticias/eesc-usp-sp-anuncia-concurso-publico-para-professor-doutor-em-telecomunicacoes",
    "end_date": "2026-05-15",
    "vacancies": 1,
    "salary_text": "R$ 16.353,01",
    "salary_value": 16353.01
  },
  {
    "title": "USP - Universidade de São Paulo",
    "link": "https://www.pciconcursos.com.br/noticias/usp-abre-concurso-publico-para-professor-doutor-no-departamento-de-fisica-nuclear",
    "end_date": "2026-06-08",
    "vacancies": 1,
    "salary_text": "R$ 16.353,01",
    "salary_value": 16353.01
  },
  {
    "title": "PM/SP - Polícia Militar do Estado de São Paulo",
    "link": "https://www.pciconcursos.com.br/noticias/policia-militar-sp-abre-concurso-com-36-vagas-para-medicos-em-diversas-especialidades",
    "end_date": "2026-05-07",
    "vacancies": 36,
    "salary_text": "R$ 9.832,41",
    "salary_value": 9832.41
  },
  {
    "title": "UNICAMP - Universidade Estadual de Campinas",
    "link": "https://www.pciconcursos.com.br/noticias/unicamp-sp-abre-vagas-para-o-cargo-de-professor-doutor-no-instituto-de-artes",
    "end_date": "2026-05-14",
    "vacancies": 3,
    "salary_text": "R$ 16.353,30",
    "salary_value": 16353.3
  },
  {
    "title": "EESC-USP - Escola de Engenharia de São Carlos da Universidade de São Paulo",
    "link": "https://www.pciconcursos.com.br/noticias/eesc-usp-sp-abre-concurso-publico-para-professor-doutor-no-departamento-de-engenharia-de-transportes",
    "end_date": "2026-06-10",
    "vacancies": 1,
    "salary_text": "R$ 16.353,01",
    "salary_value": 16353.01
  },
  {
    "title": "EEUSP - Escola de Enfermagem da Universidade de São Paulo",
    "link": "https://www.pciconcursos.com.br/noticias/usp-abre-vaga-em-concurso-publico-para-professor-titular-na-escola-de-enfermagem",
    "end_date": "2026-09-18",
    "vacancies": 1,
    "salary_text": "R$ 24.309,11",
    "salary_value": 24309.11
  },
  {
    "title": "FMUSP - Faculdade de Medicina da Universidade de São Paulo",
    "link": "https://www.pciconcursos.com.br/noticias/fmusp-sp-abre-concurso-publico-para-professor-doutor-no-departamento-de-oftalmologia-e-otorrinolaringologia",
    "end_date": "2026-05-06",
    "vacancies": 1,
    "salary_text": "R$ 7.195,43",
    "salary_value": 7195.43
  },
  {
    "title": "FMUSP - Faculdade de Medicina da Universidade de São Paulo",
    "link": "https://www.pciconcursos.com.br/noticias/fmusp-sp-abre-vaga-para-professor-doutor-na-area-de-psiquiatria-geral",
    "end_date": "2026-05-07",
    "vacancies": 1,
    "salary_text": "R$ 7.195,43",
    "salary_value": 7195.43
  },
  {
    "title": "FMUSP - Faculdade de Medicina da Universidade de São Paulo",
    "link": "https://www.pciconcursos.com.br/noticias/fmusp-sp-abre-concurso-publico-para-o-cargo-de-professor-doutor-no-departamento-de-patologia",
    "end_date": "2026-05-08",
    "vacancies": 1,
    "salary_text": "R$ 7.195,43",
    "salary_value": 7195.43
  },
  {
    "title": "USP - Universidade de São Paulo",
    "link": "https://www.pciconcursos.com.br/noticias/usp-abre-vaga-em-concurso-publico-para-professor-doutor-na-faculdade-de-medicina",
    "end_date": "2026-05-07",
    "vacancies": 1,
    "salary_text": "R$ 7.195,43",
    "salary_value": 7195.43
  },
  {
    "title": "USP - Universidade de São Paulo",
    "link": "https://www.pciconcursos.com.br/noticias/usp-abre-concurso-para-professor-doutor-de-patologia-clinica-na-faculdade-de-medicina",
    "end_date": "2026-05-06",
    "vacancies": 1,
    "salary_text": "R$ 7.195,43",
    "salary_value": 7195.43
  },
  {
    "title": "FMRP-USP - Faculdade de Medicina de Ribeirão Preto da Universidade de São Paulo",
    "link": "https://www.pciconcursos.com.br/noticias/fmrp-usp-abre-concurso-para-professor-doutor-no-departamento-de-patologia-e-medicina-legal",
    "end_date": "2026-06-15",
    "vacancies": 1,
    "salary_text": "R$ 16.353,01",
    "salary_value": 16353.01
  },
  {
    "title": "UNICAMP - Universidade Estadual de Campinas",
    "link": "https://www.pciconcursos.com.br/noticias/unicamp-sp-abre-concursos-para-professores-doutores-no-instituto-de-computacao",
    "end_date": "2026-05-08",
    "vacancies": 2,
    "salary_text": "R$ 16.353,30",
    "salary_value": 16353.3
  },
  {
    "title": "UNICAMP - Universidade Estadual de Campinas",
    "link": "https://www.pciconcursos.com.br/noticias/unicamp-sp-abre-concursos-para-o-professor-doutor-no-instituto-de-computacao",
    "end_date": "2026-05-08",
    "vacancies": 2,
    "salary_text": "R$ 16.353,30",
    "salary_value": 16353.3
  },
  {
    "title": "USP - Universidade de São Paulo",
    "link": "https://www.pciconcursos.com.br/noticias/usp-abre-concurso-para-professor-doutor-no-departamento-de-imunologia",
    "end_date": "2026-05-18",
    "vacancies": 1,
    "salary_text": "R$ 16.353,01",
    "salary_value": 16353.01
  },
  {
    "title": "USP - Universidade de São Paulo",
    "link": "https://www.pciconcursos.com.br/noticias/usp-abre-concurso-publico-para-professor-doutor-na-area-de-farmacologia-integrativa",
    "end_date": "2026-06-17",
    "vacancies": 1,
    "salary_text": "R$ 16.353,01",
    "salary_value": 16353.01
  },
  {
    "title": "UNESP - Universidade Estadual Paulista \"Júlio de Mesquita Filho\"",
    "link": "https://www.pciconcursos.com.br/noticias/unesp-abre-concurso-publico-com-salario-de-14-7-mil-para-pesquisador-iv",
    "end_date": "2026-05-05",
    "vacancies": 1,
    "salary_text": "R$ 14.717,71",
    "salary_value": 14717.71
  },
  {
    "title": "Prefeitura de Itapeva",
    "link": "https://www.pciconcursos.com.br/noticias/prefeitura-de-itapeva-sp-abre-concurso-com-salarios-de-ate-5-7-mil",
    "end_date": "2026-05-07",
    "vacancies": 23,
    "salary_text": "R$ 5.721,43",
    "salary_value": 5721.43
  },
  {
    "title": "Prefeitura da Estância Balneária de Itanhaém",
    "link": "https://www.pciconcursos.com.br/noticias/prefeitura-de-itanhaem-sp-abre-processo-seletivo-com-100-vagas",
    "end_date": "2026-05-14",
    "vacancies": 100,
    "salary_text": "R$ 2.560,00",
    "salary_value": 2560.0
  },
  {
    "title": "Prefeitura de Bauru",
    "link": "https://www.pciconcursos.com.br/noticias/prefeitura-de-bauru-sp-reabre-concurso-publico-com-vaga-para-assistente-social",
    "end_date": "2026-05-07",
    "vacancies": 11,
    "salary_text": "R$ 5.808,50",
    "salary_value": 5808.5
  },
  {
    "title": "UNESP - Universidade Estadual Paulista \"Julio de Mesquita Filho\"",
    "link": "https://www.pciconcursos.com.br/noticias/unesp-sp-abre-concurso-publico-para-o-cargo-de-professor-titular-em-araraquara",
    "end_date": "2026-05-20",
    "vacancies": 1,
    "salary_text": "R$ 24.309,11",
    "salary_value": 24309.11
  },
  {
    "title": "USP - Universidade de São Paulo",
    "link": "https://www.pciconcursos.com.br/noticias/faculdade-de-medicina-de-bauru-da-usp-sp-abre-concursos-com-vagas-para-o-cargo-de-professor-doutor",
    "end_date": "2026-07-01",
    "vacancies": 5,
    "salary_text": "R$ 7.195,43",
    "salary_value": 7195.43
  },
  {
    "title": "IFUSP - Instituto de Física da Universidade de São Paulo",
    "link": "https://www.pciconcursos.com.br/noticias/ifusp-sp-abre-concurso-publico-para-professor-doutor-na-area-de-fisica",
    "end_date": "2026-07-07",
    "vacancies": 1,
    "salary_text": "R$ 16.353,01",
    "salary_value": 16353.01
  },
  {
    "title": "UNESP - Faculdade de Medicina Veterinária de Araçatuba",
    "link": "https://www.pciconcursos.com.br/noticias/unesp-abre-concurso-publico-para-professor-titular-de-medicina-veterinaria-em-aracatuba-sp",
    "end_date": "2026-05-27",
    "vacancies": 1,
    "salary_text": "R$ 24.309,11",
    "salary_value": 24309.11
  },
  {
    "title": "UNICAMP - Universidade Estadual de Campinas",
    "link": "https://www.pciconcursos.com.br/noticias/unicamp-sp-abre-concurso-publico-para-professor-titular-no-instituto-de-filosofia-e-ciencias-humanas",
    "end_date": "2026-05-11",
    "vacancies": 1,
    "salary_text": "R$ 24.309,11",
    "salary_value": 24309.11
  },
  {
    "title": "UNESP - Universidade Estadual Paulista",
    "link": "https://www.pciconcursos.com.br/noticias/unesp-abre-vaga-para-professor-titular-na-faculdade-de-medicina-veterinaria-de-aracatuba-sp",
    "end_date": "2026-05-27",
    "vacancies": 1,
    "salary_text": "R$ 24.309,11",
    "salary_value": 24309.11
  },
  {
    "title": "USP - Universidade de São Paulo",
    "link": "https://www.pciconcursos.com.br/noticias/poli-usp-abre-concursos-para-professores-doutores-no-departamento-de-engenharia-metalurgica-e-de-materiais",
    "end_date": "2026-07-06",
    "vacancies": 2,
    "salary_text": "R$ 16.353,01",
    "salary_value": 16353.01
  },
  {
    "title": "USP - Universidade de São Paulo",
    "link": "https://www.pciconcursos.com.br/noticias/usp-abre-processo-seletivo-para-professor-no-departamento-de-engenharia-de-transportes",
    "end_date": "2026-05-05",
    "vacancies": 1,
    "salary_text": "R$ 2.834,61",
    "salary_value": 2834.61
  },
  {
    "title": "Prefeitura de Parisi",
    "link": "https://www.pciconcursos.com.br/noticias/prefeitura-de-parisi-sp-abre-novo-concurso-publico-com-salarios-de-ate-5-5-mil",
    "end_date": "2026-05-06",
    "vacancies": 9,
    "salary_text": "R$ 5.512,80",
    "salary_value": 5512.8
  },
  {
    "title": "UNESP - Universidade Estadual Paulista \"Júlio de Mesquita Filho\"",
    "link": "https://www.pciconcursos.com.br/noticias/unesp-abre-concurso-publico-para-professor-assistente-de-meteorologia-em-bauru-sp",
    "end_date": "2026-05-12",
    "vacancies": 1,
    "salary_text": "R$ 16.353,01",
    "salary_value": 16353.01
  },
  {
    "title": "Prefeitura de Promissão",
    "link": "https://www.pciconcursos.com.br/noticias/prefeitura-de-promissao-sp-abre-concurso-publico-com-diversas-vagas-e-cadastro-de-reserva",
    "end_date": "2026-05-07",
    "vacancies": 194,
    "salary_text": "R$ 6.376,74",
    "salary_value": 6376.74
  },
  {
    "title": "Câmara de Votorantim",
    "link": "https://www.pciconcursos.com.br/noticias/camara-de-votorantim-sp-abre-concurso-publico-com-salarios-de-ate-7-5-mil",
    "end_date": "2026-05-26",
    "vacancies": 8,
    "salary_text": "R$ 7.521,28",
    "salary_value": 7521.28
  },
  {
    "title": "UNESP - Universidade Estadual Paulista",
    "link": "https://www.pciconcursos.com.br/noticias/unesp-abre-concurso-para-professor-substituto-de-engenharia-mecanica-em-guaratingueta-sp",
    "end_date": "2026-05-08",
    "vacancies": 1,
    "salary_text": "R$ 3.379,43",
    "salary_value": 3379.43
  },
  {
    "title": "UNICAMP - Universidade Estadual de Campinas",
    "link": "https://www.pciconcursos.com.br/noticias/unicamp-sp-abre-vagas-para-professores-doutores-no-instituto-de-artes",
    "end_date": "2026-05-13",
    "vacancies": 2,
    "salary_text": "R$ 16.353,30",
    "salary_value": 16353.3
  },
  {
    "title": "Prefeitura de Mairiporã",
    "link": "https://www.pciconcursos.com.br/noticias/prefeitura-de-mairipora-sp-abre-processo-seletivo-para-monitor-social-e-peb-i-educacao-infantil",
    "end_date": "2026-05-14",
    "vacancies": 2,
    "salary_text": "R$ 3.978,41",
    "salary_value": 3978.41
  },
  {
    "title": "Prefeitura de São Vicente",
    "link": "https://www.pciconcursos.com.br/noticias/prefeitura-de-sao-vicente-sp-abre-concurso-publico-com-salarios-de-ate-3-3-mil",
    "end_date": "2026-05-07",
    "vacancies": 59,
    "salary_text": "R$ 3.385,13",
    "salary_value": 3385.13
  },
  {
    "title": "Prefeitura do Município de Santana de Parnaíba",
    "link": "https://www.pciconcursos.com.br/noticias/prefeitura-de-santana-de-parnaiba-sp-abre-concurso-publico-com-vagas-para-medicos",
    "end_date": "2026-05-10",
    "vacancies": 25,
    "salary_text": "R$ 14.493,23",
    "salary_value": 14493.23
  },
  {
    "title": "UNESP - Universidade Estadual Paulista",
    "link": "https://www.pciconcursos.com.br/noticias/unesp-abre-vaga-para-professor-titular-no-instituto-de-geociencias-e-ciencias-exatas-de-rio-claro-sp",
    "end_date": "2026-05-29",
    "vacancies": 1,
    "salary_text": "R$ 24.309,11",
    "salary_value": 24309.11
  },
  {
    "title": "UNICAMP - Universidade Estadual de Campinas",
    "link": "https://www.pciconcursos.com.br/noticias/unicamp-sp-abre-concurso-para-professor-doutor-na-area-de-tecnica-cirurgica",
    "end_date": "2026-05-22",
    "vacancies": 1,
    "salary_text": "R$ 16.353,30",
    "salary_value": 16353.3
  },
  {
    "title": "Prefeitura de Bebedouro",
    "link": "https://www.pciconcursos.com.br/noticias/prefeitura-de-bebedouro-sp-abre-processo-seletivo-para-a-area-da-educacao",
    "end_date": "2026-05-07",
    "salary_text": "R$ 26,94",
    "salary_value": 26.94
  },
  {
    "title": "Prefeitura de Elias Fausto",
    "link": "https://www.pciconcursos.com.br/noticias/prefeitura-de-elias-fausto-sp-abre-concursos-publicos-para-cargos-de-nivel-superior",
    "end_date": "2026-05-14",
    "vacancies": 27,
    "salary_text": "R$ 7.788,12",
    "salary_value": 7788.12
  },
  {
    "title": "CREFONO-2/SP - Conselho Regional de Fonoaudiologia de São Paulo",
    "link": "https://www.pciconcursos.com.br/noticias/crefono-2-sp-abre-concurso-publico-com-vagas-para-agente-e-analista-de-fiscalizacao",
    "end_date": "2026-05-20",
    "vacancies": 5,
    "salary_text": "R$ 5.246,54",
    "salary_value": 5246.54
  },
  {
    "title": "Prefeitura de Elias Fausto",
    "link": "https://www.pciconcursos.com.br/noticias/prefeitura-de-elias-fausto-sp-abre-concurso-com-vagas-imediatas-e-cadastro-de-reserva",
    "end_date": "2026-05-14",
    "vacancies": 54,
    "salary_text": "R$ 3.242,00",
    "salary_value": 3242.0
  },
  {
    "title": "Prefeitura de Lupércio",
    "link": "https://www.pciconcursos.com.br/noticias/prefeitura-de-lupercio-sp-abre-concurso-e-processo-seletivo-para-diversos-cargos",
    "end_date": "2026-05-11",
    "vacancies": 4,
    "salary_text": "R$ 5.250,00",
    "salary_value": 5250.0
  },
  {
    "title": "Prefeitura de Rio Claro",
    "link": "https://www.pciconcursos.com.br/noticias/prefeitura-de-rio-claro-sp-abre-concurso-publico-com-salarios-de-ate-7-1-mil",
    "end_date": "2026-05-11",
    "vacancies": 21,
    "salary_text": "R$ 7.193,63",
    "salary_value": 7193.63
  },
  {
    "title": "UNESP - Universidade Estadual Paulista",
    "link": "https://www.pciconcursos.com.br/noticias/unesp-publica-edital-para-professor-substituto-de-biotecnologia-industrial-em-araraquara-sp",
    "end_date": "2026-05-06",
    "vacancies": 1,
    "salary_text": "R$ 3.379,43",
    "salary_value": 3379.43
  },
  {
    "title": "UNICAMP - Universidade Estadual de Campinas",
    "link": "https://www.pciconcursos.com.br/noticias/unicamp-sp-abre-concurso-para-professor-doutor-em-radiologia-diagnostica-e-terapeutica",
    "end_date": "2026-06-10",
    "vacancies": 1,
    "salary_text": "R$ 16.353,30",
    "salary_value": 16353.3
  },
  {
    "title": "UNICAMP - Universidade Estadual de Campinas",
    "link": "https://www.pciconcursos.com.br/noticias/unicamp-sp-abre-concurso-publico-para-professor-doutor-na-faculdade-de-ciencias-medicas",
    "end_date": "2026-05-22",
    "vacancies": 1,
    "salary_text": "R$ 16.353,30",
    "salary_value": 16353.3
  },
  {
    "title": "Câmara de Taiúva",
    "link": "https://www.pciconcursos.com.br/noticias/camara-de-taiuva-sp-abre-concurso-para-cargo-de-agente-de-servicos-gerais",
    "end_date": "2026-05-18",
    "vacancies": 1,
    "salary_text": "R$ 2.340,99",
    "salary_value": 2340.99
  },
  {
    "title": "Prefeitura de Suzano",
    "link": "https://www.pciconcursos.com.br/noticias/prefeitura-de-suzano-sp-lanca-concurso-publico-com-salarios-de-ate-12-mil",
    "end_date": "2026-05-14",
    "salary_text": "R$ 12.062,91",
    "salary_value": 12062.91
  },
  {
    "title": "Câmara de Santo Antônio de Posse",
    "link": "https://www.pciconcursos.com.br/noticias/camara-de-santo-antonio-de-posse-sp-abre-concurso-publico-para-tecnico-financeiro",
    "end_date": "2026-05-24",
    "vacancies": 1,
    "salary_text": "R$ 4.000,00",
    "salary_value": 4000.0
  },
  {
    "title": "ICMBio - Instituto Chico Mendes de Conservação da Biodiversidade",
    "link": "https://www.pciconcursos.com.br/noticias/icmbio-sp-abre-processo-seletivo-para-agentes-temporarios-ambientais-em-ipero",
    "end_date": "2026-05-13"
  },
  {
    "title": "Câmara de Presidente Prudente",
    "link": "https://www.pciconcursos.com.br/noticias/camara-de-presidente-prudente-sp-abre-concurso-publico-com-salarios-de-ate-22-mil",
    "end_date": "2026-05-21",
    "vacancies": 4,
    "salary_text": "R$ 22.010,63",
    "salary_value": 22010.63
  },
  {
    "title": "HCFMRP-USP - Hospital das Clínicas da Faculdade de Medicina de Ribeirão Preto da Universidade de São Paulo",
    "link": "https://www.pciconcursos.com.br/noticias/hcfmrp-usp-abre-concurso-para-medico-na-area-de-neurologia-pediatrica",
    "end_date": "2026-05-08",
    "vacancies": 1,
    "salary_text": "R$ 5.979,93",
    "salary_value": 5979.93
  },
  {
    "title": "HCFMRP-USP - Hospital das Clínicas da Faculdade de Medicina de Ribeirão Preto da Universidade de São Paulo",
    "link": "https://www.pciconcursos.com.br/noticias/hcfmrp-usp-abre-concurso-publico-para-medico-ginecologista",
    "end_date": "2026-05-08",
    "vacancies": 1,
    "salary_text": "R$ 5.979,93",
    "salary_value": 5979.93
  },
  {
    "title": "Prefeitura da Estância Turística de São Roque",
    "link": "https://www.pciconcursos.com.br/noticias/prefeitura-de-sao-roque-sp-abre-processo-seletivo-para-a-area-da-educacao",
    "end_date": "2026-05-19",
    "salary_text": "R$ 2.685,84",
    "salary_value": 2685.84
  },
  {
    "title": "Prefeitura do Município de Carapicuíba",
    "link": "https://www.pciconcursos.com.br/noticias/prefeitura-de-carapicuiba-sp-abre-concurso-publico-com-salarios-de-ate-4-5-mil",
    "end_date": "2026-05-21",
    "vacancies": 2,
    "salary_text": "R$ 4.567,23",
    "salary_value": 4567.23
  },
  {
    "title": "UNESP - Faculdade de Ciências e Letras de Assis",
    "link": "https://www.pciconcursos.com.br/noticias/unesp-de-assis-sp-abre-concurso-para-professor-assistente-na-faculdade-de-ciencias-e-letras",
    "end_date": "2026-05-27",
    "vacancies": 1,
    "salary_text": "R$ 16.353,01",
    "salary_value": 16353.01
  },
  {
    "title": "UNESP - Faculdade de Odontologia Campus de Araçatuba",
    "link": "https://www.pciconcursos.com.br/noticias/faculdade-de-odontologia-da-unesp-abre-vaga-para-professor-substituto-em-aracatuba-sp",
    "end_date": "2026-05-11",
    "vacancies": 1,
    "salary_text": "R$ 3.379,43",
    "salary_value": 3379.43
  },
  {
    "title": "UNESP - Universidade Estadual Paulista",
    "link": "https://www.pciconcursos.com.br/noticias/unesp-abre-concurso-para-professor-substituto-em-odontologia-no-campus-de-sao-jose-dos-campos-sp",
    "end_date": "2026-05-06",
    "vacancies": 1,
    "salary_text": "R$ 3.379,43",
    "salary_value": 3379.43
  },
  {
    "title": "UNESP - Universidade Estadual Paulista",
    "link": "https://www.pciconcursos.com.br/noticias/unesp-abre-concurso-publico-para-professor-substituto-de-educacao-fisica-em-presidente-prudente-sp",
    "end_date": "2026-05-06",
    "vacancies": 1,
    "salary_text": "R$ 3.379,43",
    "salary_value": 3379.43
  },
  {
    "title": "UNESP - Universidade Estadual Paulista",
    "link": "https://www.pciconcursos.com.br/noticias/unesp-abre-concurso-publico-para-professor-substituto-de-fonoaudiologia-em-marilia-sp",
    "end_date": "2026-05-06",
    "vacancies": 1,
    "salary_text": "R$ 3.379,43",
    "salary_value": 3379.43
  },
  {
    "title": "Prefeitura de Suzano",
    "link": "https://www.pciconcursos.com.br/noticias/prefeitura-de-suzano-sp-publica-retificacao-em-concurso-com-ganhos-que-chegam-a-12-mil",
    "end_date": "2026-05-14",
    "salary_text": "R$ 12.062,91",
    "salary_value": 12062.91
  },
  {
    "title": "FERSB - Fundação Estatal Regional de Saúde da Região de Bauru",
    "link": "https://www.pciconcursos.com.br/noticias/fersb-sp-publica-processo-seletivo-para-assistente-administrativo-e-agente-de-administracao",
    "end_date": "2026-05-05",
    "vacancies": 2,
    "salary_text": "R$ 3.589,94",
    "salary_value": 3589.94
  },
  {
    "title": "FunGOTA - Fundação Municipal Irene Siqueira Alves \"Vovó Mocinha\", Maternidade Gota de Leite de Araraquara",
    "link": "https://www.pciconcursos.com.br/noticias/fungota-araraquara-sp-abre-concurso-e-processo-seletivo-para-diversos-cargos",
    "end_date": "2026-05-11",
    "vacancies": 6,
    "salary_text": "R$ 10.311,80",
    "salary_value": 10311.8
  },
  {
    "title": "ICMBio - Instituto Chico Mendes de Conservação da Biodiversidade",
    "link": "https://www.pciconcursos.com.br/noticias/icmbio-sp-publica-edital-para-selecao-de-agentes-temporarios-ambientais-em-buri",
    "end_date": "2026-05-13"
  },
  {
    "title": "Prefeitura de Mairinque",
    "link": "https://www.pciconcursos.com.br/noticias/prefeitura-de-mairinque-sp-abre-processo-seletivo-para-professores",
    "end_date": "2026-05-05",
    "salary_text": "R$ 27,98",
    "salary_value": 27.98
  },
  {
    "title": "Fundação Estatal Regional de Saúde e Desenvolvimento Social da Bacia do Juquery",
    "link": "https://www.pciconcursos.com.br/noticias/fundacao-da-bacia-do-juquery-sp-publica-retificacoes-em-processo-seletivo",
    "end_date": "2026-05-11",
    "vacancies": 46,
    "salary_text": "R$ 4.605,39",
    "salary_value": 4605.39
  },
  {
    "title": "Prefeitura de Campinas",
    "link": "https://www.pciconcursos.com.br/noticias/prefeitura-de-campinas-sp-abre-concurso-para-tradutor-e-interprete-de-libras",
    "end_date": "2026-06-29",
    "vacancies": 5,
    "salary_text": "R$ 4.101,84",
    "salary_value": 4101.84
  },
  {
    "title": "Prefeitura de Lindoia",
    "link": "https://www.pciconcursos.com.br/noticias/prefeitura-de-lindoia-sp-abre-concurso-publico-com-salarios-de-ate-4-5-mil",
    "end_date": "2026-05-19",
    "vacancies": 9,
    "salary_text": "R$ 4.508,68",
    "salary_value": 4508.68
  },
  {
    "title": "Prefeitura de Bauru",
    "link": "https://www.pciconcursos.com.br/noticias/prefeitura-de-bauru-sp-abre-concursos-publicos-para-diversos-cargos",
    "end_date": "2026-05-25",
    "vacancies": 5,
    "salary_text": "R$ 6.105,89",
    "salary_value": 6105.89
  },
  {
    "title": "Prefeitura de Taguaí",
    "link": "https://www.pciconcursos.com.br/noticias/prefeitura-de-taguai-sp-abre-concurso-com-salarios-de-ate-4-4-mil",
    "end_date": "2026-05-12",
    "vacancies": 3,
    "salary_text": "R$ 4.433,43",
    "salary_value": 4433.43
  },
  {
    "title": "UNESP - Universidade Estadual Paulista",
    "link": "https://www.pciconcursos.com.br/noticias/unesp-abre-concurso-para-professor-substituto-de-probabilidade-e-estatistica-em-botucatu",
    "end_date": "2026-05-11",
    "vacancies": 1,
    "salary_text": "R$ 3.379,43",
    "salary_value": 3379.43
  },
  {
    "title": "Prefeitura de Santa Isabel",
    "link": "https://www.pciconcursos.com.br/noticias/prefeitura-de-santa-isabel-sp-abre-processo-seletivo-com-vagas-para-professores",
    "end_date": "2026-05-13",
    "vacancies": 28,
    "salary_text": "R$ 3.802,59",
    "salary_value": 3802.59
  },
  {
    "title": "ICMBio - Instituto Chico Mendes de Conservação da Biodiversidade",
    "link": "https://www.pciconcursos.com.br/noticias/icmbio-sp-abre-selecao-para-agentes-temporarios-ambientais-em-ipero",
    "end_date": "2026-05-13",
    "vacancies": 1
  },
  {
    "title": "Prefeitura de Emilianópolis",
    "link": "https://www.pciconcursos.com.br/noticias/prefeitura-de-emilianopolis-sp-abre-concurso-publico-com-remuneracoes-de-ate-6-4-mil",
    "end_date": "2026-05-07",
    "vacancies": 14,
    "salary_text": "R$ 6.475,61",
    "salary_value": 6475.61
  },
  {
    "title": "Câmara de Santa Isabel",
    "link": "https://www.pciconcursos.com.br/noticias/camara-de-santa-isabel-sp-abre-concurso-com-salarios-de-ate-9-9-mil",
    "end_date": "2026-05-25",
    "vacancies": 1,
    "salary_text": "R$ 9.916,51",
    "salary_value": 9916.51
  },
  {
    "title": "EsPCEx - Escola Preparatória de Cadetes do Exército",
    "link": "https://www.pciconcursos.com.br/noticias/espcex-sp-abre-concurso-com-440-vagas-para-curso-de-formacao-de-oficiais-de-carreira",
    "end_date": "2026-05-29",
    "vacancies": 440
  },
  {
    "title": "Prefeitura de Maracaí",
    "link": "https://www.pciconcursos.com.br/noticias/prefeitura-de-maracai-sp-abre-concurso-publico-com-salarios-de-ate-18199",
    "end_date": "2026-05-07",
    "vacancies": 15,
    "salary_text": "R$ 18.199,95",
    "salary_value": 18199.95
  },
  {
    "title": "CAU/SP - Conselho de Arquitetura e Urbanismo de São Paulo",
    "link": "https://www.pciconcursos.com.br/noticias/cau-sp-abre-concurso-publico-com-vagas-para-assistentes-e-analistas-tecnicos",
    "end_date": "2026-06-03",
    "vacancies": 36,
    "salary_text": "R$ 10.046,54",
    "salary_value": 10046.54
  },
  {
    "title": "FAMESP - Fundação para o Desenvolvimento Médico e Hospitalar",
    "link": "https://www.pciconcursos.com.br/noticias/famesp-abre-processos-seletivos-com-salarios-de-ate-11620-em-itapetininga-e-botucatu",
    "end_date": "2026-05-06",
    "vacancies": 12,
    "salary_text": "R$ 11.620,63",
    "salary_value": 11620.63
  },
  {
    "title": "UNESP - Universidade Estadual Paulista",
    "link": "https://www.pciconcursos.com.br/noticias/unesp-abre-concurso-publico-para-professor-substituto-de-matematica-no-campus-de-presidente-prudente-sp",
    "end_date": "2026-05-12",
    "vacancies": 1,
    "salary_text": "R$ 3.379,43",
    "salary_value": 3379.43
  },
  {
    "title": "UNESP - Universidade Estadual Paulista",
    "link": "https://www.pciconcursos.com.br/noticias/unesp-abre-concurso-com-vaga-para-professor-substituto-em-sao-jose-dos-campos-sp",
    "end_date": "2026-05-11",
    "vacancies": 1,
    "salary_text": "R$ 3.379,43",
    "salary_value": 3379.43
  },
  {
    "title": "UNESP - Universidade Estadual Paulista",
    "link": "https://www.pciconcursos.com.br/noticias/unesp-abre-vaga-para-professor-substituto-de-matematica-em-rio-claro-sp",
    "end_date": "2026-05-12",
    "vacancies": 1,
    "salary_text": "R$ 3.379,43",
    "salary_value": 3379.43
  },
  {
    "title": "UNESP - Universidade Estadual Paulista",
    "link": "https://www.pciconcursos.com.br/noticias/unesp-abre-concurso-para-professor-substituto-na-area-de-ciencias-humanas-em-bauru-sp",
    "end_date": "2026-05-11",
    "vacancies": 1,
    "salary_text": "R$ 8.578,39",
    "salary_value": 8578.39
  },
  {
    "title": "UNESP - Universidade Estadual Paulista",
    "link": "https://www.pciconcursos.com.br/noticias/unesp-abre-vaga-em-concurso-publico-para-professor-substituto-no-campus-sao-joao-da-boa-vista-sp",
    "end_date": "2026-05-13",
    "vacancies": 1,
    "salary_text": "R$ 3.379,43",
    "salary_value": 3379.43
  },
  {
    "title": "UNESP - Universidade Estadual Paulista",
    "link": "https://www.pciconcursos.com.br/noticias/unesp-abre-cinco-concursos-publicos-para-professores-substitutos-em-presidente-prudente-sp",
    "end_date": "2026-05-11",
    "vacancies": 5,
    "salary_text": "R$ 3.379,43",
    "salary_value": 3379.43
  },
  {
    "title": "UNICAMP - Universidade Estadual de Campinas",
    "link": "https://www.pciconcursos.com.br/noticias/unicamp-sp-abre-concurso-publico-para-professor-doutor-na-area-de-enfermagem",
    "end_date": "2026-06-02",
    "vacancies": 1,
    "salary_text": "R$ 16.353,30",
    "salary_value": 16353.3
  },
  {
    "title": "Prefeitura da Estância Balneária de Praia Grande",
    "link": "https://www.pciconcursos.com.br/noticias/prefeitura-de-praia-grande-sp-abre-concursos-publicos-com-salarios-de-ate-21-8-mil",
    "end_date": "2026-05-20",
    "vacancies": 23,
    "salary_text": "R$ 21.809,43",
    "salary_value": 21809.43
  },
  {
    "title": "Câmara da Estância de Ibirá",
    "link": "https://www.pciconcursos.com.br/noticias/camara-de-estancia-de-ibira-sp-abre-concurso-para-procurador-juridico",
    "end_date": "2026-05-11",
    "vacancies": 1,
    "salary_text": "R$ 12.900,00",
    "salary_value": 12900.0
  },
  {
    "title": "FUNCAMP - Fundação de Desenvolvimento da Unicamp",
    "link": "https://www.pciconcursos.com.br/noticias/funcamp-sp-abre-processo-seletivo-para-o-cargo-de-analista-de-sistemas-junior",
    "end_date": "2026-05-12",
    "vacancies": 1,
    "salary_text": "R$ 5.100,00",
    "salary_value": 5100.0
  },
  {
    "title": "Prefeitura de Sete Barras",
    "link": "https://www.pciconcursos.com.br/noticias/prefeitura-de-sete-barras-sp-abre-processo-seletivo-com-salarios-de-ate-14-mil",
    "end_date": "2026-05-07",
    "vacancies": 79,
    "salary_text": "R$ 14.192,22",
    "salary_value": 14192.22
  },
  {
    "title": "Câmara de Arujá",
    "link": "https://www.pciconcursos.com.br/noticias/camara-de-aruja-sp-abre-concurso-publico-com-salarios-de-ate-15-6-mil",
    "end_date": "2026-07-13",
    "vacancies": 5,
    "salary_text": "R$ 15.659,70",
    "salary_value": 15659.7
  },
  {
    "title": "Prefeitura de Rio Claro",
    "link": "https://www.pciconcursos.com.br/noticias/prefeitura-de-rio-claro-sp-publica-retificacoes-em-concurso-publico",
    "end_date": "2026-05-11",
    "vacancies": 21,
    "salary_text": "R$ 7.193,63",
    "salary_value": 7193.63
  },
  {
    "title": "Câmara de Tietê",
    "link": "https://www.pciconcursos.com.br/noticias/camara-de-tiete-sp-abre-concurso-para-analista-de-compras-e-licitacoes",
    "end_date": "2026-05-26",
    "vacancies": 1,
    "salary_text": "R$ 6.027,86",
    "salary_value": 6027.86
  },
  {
    "title": "HCFMRP - USP - Hospital das Clínicas da Faculdade de Medicina de Ribeirão Preto da Universidade de São Paulo",
    "link": "https://www.pciconcursos.com.br/noticias/hcfmrp-usp-abre-concurso-publico-com-vaga-para-medico-geriatra",
    "end_date": "2026-05-15",
    "vacancies": 1,
    "salary_text": "R$ 5.979,93",
    "salary_value": 5979.93
  },
  {
    "title": "Prefeitura de Nova Canaã Paulista",
    "link": "https://www.pciconcursos.com.br/noticias/prefeitura-de-nova-canaa-paulista-sp-abre-concurso-publico-com-salarios-de-ate-5757",
    "end_date": "2026-05-27",
    "vacancies": 18,
    "salary_text": "R$ 5.757,29",
    "salary_value": 5757.29
  },
  {
    "title": "Prefeitura de Jardinópolis",
    "link": "https://www.pciconcursos.com.br/noticias/prefeitura-de-jardinopolis-sp-abre-concurso-publico-para-diversos-cargos",
    "end_date": "2026-06-08",
    "vacancies": 87,
    "salary_text": "R$ 5.883,47",
    "salary_value": 5883.47
  },
  {
    "title": "Prefeitura de Jumirim",
    "link": "https://www.pciconcursos.com.br/noticias/prefeitura-de-jumirim-sp-abre-concurso-publico-para-assistente-administrativo-e-fonoaudiologo",
    "end_date": "2026-05-14",
    "vacancies": 2,
    "salary_text": "R$ 4.625,27",
    "salary_value": 4625.27
  },
  {
    "title": "Prefeitura de Martinópolis",
    "link": "https://www.pciconcursos.com.br/noticias/prefeitura-de-martinopolis-sp-abre-concurso-publico-com-salarios-de-ate-16-2-mil",
    "end_date": "2026-05-13",
    "vacancies": 12,
    "salary_text": "R$ 16.246,98",
    "salary_value": 16246.98
  },
  {
    "title": "Prefeitura de Palmares Paulista",
    "link": "https://www.pciconcursos.com.br/noticias/prefeitura-de-palmares-paulista-sp-abre-concurso-para-fiscal-tributario",
    "end_date": "2026-05-12",
    "vacancies": 1,
    "salary_text": "R$ 2.993,47",
    "salary_value": 2993.47
  },
  {
    "title": "SAAE - Serviço Autônomo de Água e Esgoto de Pompeia",
    "link": "https://www.pciconcursos.com.br/noticias/saae-de-pompeia-sp-abre-concurso-com-12-vagas-para-nivel-fundamental",
    "end_date": "2026-05-27",
    "vacancies": 12,
    "salary_text": "R$ 2.098,73",
    "salary_value": 2098.73
  },
  {
    "title": "Prefeitura do Município de Cajati",
    "link": "https://www.pciconcursos.com.br/noticias/prefeitura-de-cajati-sp-abre-vaga-em-processo-seletivo-para-professor-de-educacao-basica-ii",
    "end_date": "2026-05-12",
    "vacancies": 1,
    "salary_text": "R$ 3.894,43",
    "salary_value": 3894.43
  },
  {
    "title": "FMVZ - Faculdade de Medicina Veterinária e Zootecnia da USP",
    "link": "https://www.pciconcursos.com.br/noticias/fmvz-da-usp-abre-processo-seletivo-para-professor-contratado-iii-no-departamento-de-patologia",
    "end_date": "2026-05-15",
    "vacancies": 1,
    "salary_text": "R$ 2.384,62",
    "salary_value": 2384.62
  },
  {
    "title": "Prefeitura da Estância Turística de Olímpia",
    "link": "https://www.pciconcursos.com.br/noticias/prefeitura-de-olimpia-sp-abre-concurso-publico-com-salarios-de-ate-9-mil",
    "end_date": "2026-06-02",
    "vacancies": 70,
    "salary_text": "R$ 9.581,64",
    "salary_value": 9581.64
  },
  {
    "title": "Prefeitura de Bom Jesus dos Perdões",
    "link": "https://www.pciconcursos.com.br/noticias/prefeitura-de-bom-jesus-dos-perdoes-sp-abre-processo-seletivo-para-diversos-cargos",
    "end_date": "2026-05-18",
    "vacancies": 18,
    "salary_text": "R$ 4.453,63",
    "salary_value": 4453.63
  },
  {
    "title": "Prefeitura de Nantes",
    "link": "https://www.pciconcursos.com.br/noticias/prefeitura-de-nantes-sp-abre-concurso-publico-com-salarios-de-ate-6-7-mil",
    "end_date": "2026-06-05",
    "vacancies": 30,
    "salary_text": "R$ 6.772,90",
    "salary_value": 6772.9
  },
  {
    "title": "UNICAMP - Universidade Estadual de Campinas",
    "link": "https://www.pciconcursos.com.br/noticias/unicamp-sp-abre-processo-seletivo-para-professor-no-colegio-tecnico-de-campinas",
    "end_date": "2026-05-11",
    "vacancies": 1
  },
  {
    "title": "UNICAMP - Universidade Estadual de Campinas",
    "link": "https://www.pciconcursos.com.br/noticias/unicamp-sp-abre-processo-seletivo-com-vaga-para-professor-no-colegio-tecnico-de-limeira",
    "end_date": "2026-05-18",
    "vacancies": 1
  },
  {
    "title": "UNIFESP - Universidade Federal de São Paulo",
    "link": "https://www.pciconcursos.com.br/noticias/unifesp-abre-vaga-para-professor-substituto-em-enfermagem-pediatrica",
    "end_date": "2026-05-06",
    "vacancies": 1,
    "salary_text": "R$ 8.340,33",
    "salary_value": 8340.33
  },
  {
    "title": "UNIFESP - Universidade Federal de São Paulo",
    "link": "https://www.pciconcursos.com.br/noticias/unifesp-abre-processo-seletivo-para-professor-substituto-na-area-de-oftalmologia",
    "end_date": "2026-05-09",
    "vacancies": 1,
    "salary_text": "R$ 9.532,33",
    "salary_value": 9532.33
  },
  {
    "title": "Prefeitura de Palmital",
    "link": "https://www.pciconcursos.com.br/noticias/prefeitura-de-palmital-sp-retifica-concurso-publico-com-vagas-para-todos-os-niveis-de-escolaridade",
    "end_date": "2026-05-13",
    "vacancies": 14,
    "salary_text": "R$ 4.097,56",
    "salary_value": 4097.56
  },
  {
    "title": "Prefeitura de Orindiúva",
    "link": "https://www.pciconcursos.com.br/noticias/prefeitura-de-orindiuva-sp-abre-concurso-com-vagas-imediatas-e-cadastro-reserva",
    "end_date": "2026-06-01",
    "vacancies": 29,
    "salary_text": "R$ 8.091,11",
    "salary_value": 8091.11
  },
  {
    "title": "Prefeitura de Tabapuã",
    "link": "https://www.pciconcursos.com.br/noticias/prefeitura-de-tabapua-sp-abre-concurso-publico-com-salarios-de-ate-7418",
    "end_date": "2026-05-15",
    "vacancies": 23,
    "salary_text": "R$ 7.418,39",
    "salary_value": 7418.39
  },
  {
    "title": "UNIFESP - Universidade Federal de São Paulo",
    "link": "https://www.pciconcursos.com.br/noticias/unifesp-sp-abre-vaga-para-professor-de-fisioterapia-no-campus-baixada-santista",
    "end_date": "2026-05-20",
    "vacancies": 1,
    "salary_text": "R$ 6.157,29",
    "salary_value": 6157.29
  },
  {
    "title": "Caixa de Saúde e Pecúlio dos Servidores Municipais de São Vicente",
    "link": "https://www.pciconcursos.com.br/noticias/caixa-de-saude-de-sao-vicente-sp-abre-concurso-para-cargos-de-nivel-superior",
    "end_date": "2026-06-08",
    "vacancies": 3,
    "salary_text": "R$ 6.811,67",
    "salary_value": 6811.67
  },
  {
    "title": "EEL-USP - Escola de Engenharia de Lorena da Universidade de São Paulo",
    "link": "https://www.pciconcursos.com.br/noticias/eel-usp-abre-processos-seletivos-para-professores-contratados",
    "end_date": "2026-05-14",
    "vacancies": 2,
    "salary_text": "R$ 2.834,62",
    "salary_value": 2834.62
  },
  {
    "title": "FUNCAMP - Fundação de Desenvolvimento da Unicamp",
    "link": "https://www.pciconcursos.com.br/noticias/funcamp-sp-divulga-processo-seletivo-para-biologista-no-hospital-estadual-sumare",
    "end_date": "2026-05-19",
    "vacancies": 1,
    "salary_text": "R$ 4.419,79",
    "salary_value": 4419.79
  },
  {
    "title": "ICB-USP - Instituto de Ciências Biomédicas da Universidade de São Paulo",
    "link": "https://www.pciconcursos.com.br/noticias/icb-usp-abre-concurso-publico-para-o-cargo-de-professor-doutor-no-departamento-de-anatomia",
    "end_date": "2026-06-02",
    "vacancies": 1,
    "salary_text": "R$ 16.353,01",
    "salary_value": 16353.01
  },
  {
    "title": "Prefeitura da Estância Turística de Ibitinga",
    "link": "https://www.pciconcursos.com.br/noticias/prefeitura-de-ibitinga-sp-abre-concurso-publico-com-vagas-de-nivel-fundamental-e-medio",
    "end_date": "2026-05-18",
    "vacancies": 5,
    "salary_text": "R$ 2.288,17",
    "salary_value": 2288.17
  },
  {
    "title": "Prefeitura de Atibaia",
    "link": "https://www.pciconcursos.com.br/noticias/prefeitura-de-atibaia-sp-abre-processo-seletivo-para-o-cargo-de-coveiro",
    "end_date": "2026-05-21",
    "vacancies": 6,
    "salary_text": "R$ 2.220,75",
    "salary_value": 2220.75
  },
  {
    "title": "Prefeitura de Dois Córregos",
    "link": "https://www.pciconcursos.com.br/noticias/prefeitura-de-dois-corregos-sp-abre-selecao-para-professores-de-reforco",
    "end_date": "2026-06-01",
    "vacancies": 10,
    "salary_text": "R$ 3.847,97",
    "salary_value": 3847.97
  },
  {
    "title": "Prefeitura de Dois Córregos",
    "link": "https://www.pciconcursos.com.br/noticias/prefeitura-de-dois-corregos-sp-abre-concurso-com-vagas-imediatas-e-cadastro-de-reserva",
    "end_date": "2026-06-01",
    "vacancies": 21,
    "salary_text": "R$ 6.567,10",
    "salary_value": 6567.1
  },
  {
    "title": "Prefeitura de Guarulhos",
    "link": "https://www.pciconcursos.com.br/noticias/prefeitura-de-guarulhos-sp-abre-novos-concursos-para-cargos-de-nivel-superior",
    "end_date": "2026-06-02",
    "vacancies": 20,
    "salary_text": "R$ 3.791,98",
    "salary_value": 3791.98
  },
  {
    "title": "Prefeitura de Pinhalzinho",
    "link": "https://www.pciconcursos.com.br/noticias/prefeitura-de-pinhalzinho-sp-abre-processo-seletivo-para-o-cargo-de-motorista",
    "end_date": "2026-05-10",
    "vacancies": 1,
    "salary_text": "R$ 2.299,24",
    "salary_value": 2299.24
  },
  {
    "title": "Prefeitura de Tabatinga",
    "link": "https://www.pciconcursos.com.br/noticias/prefeitura-de-tabatinga-sp-abre-concurso-publico-com-salarios-de-ate-3720",
    "end_date": "2026-05-18",
    "vacancies": 3,
    "salary_text": "R$ 3.720,59",
    "salary_value": 3720.59
  },
  {
    "title": "UNESP - Universidade Estadual Paulista",
    "link": "https://www.pciconcursos.com.br/noticias/unesp-abre-concurso-para-professor-assistente-na-area-de-fisica-em-presidente-prudente",
    "end_date": "2026-06-09",
    "vacancies": 1,
    "salary_text": "R$ 16.353,01",
    "salary_value": 16353.01
  },
  {
    "title": "UNESP - Universidade Estadual Paulista \"Júlio de Mesquita Filho\"",
    "link": "https://www.pciconcursos.com.br/noticias/unesp-abre-concurso-publico-para-professor-de-ensino-medio-e-tecnico-em-bauru",
    "end_date": "2026-05-15",
    "vacancies": 1,
    "salary_text": "R$ 29,87",
    "salary_value": 29.87
  },
  {
    "title": "Prefeitura de Orindiúva",
    "link": "https://www.pciconcursos.com.br/noticias/prefeitura-de-orindiuva-sp-retifica-concurso-com-vagas-imediatas-e-cadastro-reserva",
    "end_date": "2026-06-01",
    "vacancies": 29,
    "salary_text": "R$ 8.091,11",
    "salary_value": 8091.11
  }
]